depot_client/__init__.py
depot_client/build.py
depot_client/buildkit.py
depot_client/client.py
depot_client/core_build.py
depot_client/project.py
depot_client/py.typed
depot_client/api/__init__.py
depot_client/api/depot/__init__.py
depot_client/api/depot/build/v1/build_pb2.py
depot_client/api/depot/build/v1/build_pb2_grpc.py
depot_client/api/depot/buildkit/__init__.py
depot_client/api/depot/buildkit/v1/__init__.py
depot_client/api/depot/buildkit/v1/buildkit_pb2.py
depot_client/api/depot/buildkit/v1/buildkit_pb2_grpc.py
depot_client/api/depot/core/__init__.py
depot_client/api/depot/core/v1/__init__.py
depot_client/api/depot/core/v1/build_pb2.py
depot_client/api/depot/core/v1/build_pb2_grpc.py
depot_client/api/depot/core/v1/project_pb2.py
depot_client/api/depot/core/v1/project_pb2_grpc.py
depot_client/protos/depot/build/v1/build.proto
depot_client/protos/depot/buildkit/v1/buildkit.proto
depot_client/protos/depot/core/v1/build.proto
depot_client/protos/depot/core/v1/project.proto
depot_client-0.0.22.dist-info/LICENSE
depot_client-0.0.22.dist-info/METADATA
depot_client-0.0.22.dist-info/WHEEL
depot_client-0.0.22.dist-info/top_level.txt
depot_client-0.0.22.dist-info/RECORD
